dbgcapture_mcp/__init__.py
dbgcapture_mcp/__main__.py
dbgcapture_mcp/capture_manager.py
dbgcapture_mcp/server.py
dbgcapture_mcp/dbgcapture.exe
dbgview_mcp-1.0.0.dist-info/METADATA
dbgview_mcp-1.0.0.dist-info/WHEEL
dbgview_mcp-1.0.0.dist-info/entry_points.txt
dbgview_mcp-1.0.0.dist-info/RECORD
