Metadata-Version: 2.4
Name: dbgview-mcp
Version: 1.0.0
Summary: MCP server for capturing Windows debug output
Project-URL: Homepage, https://github.com/markrussinovich/dbgview-mcp
Project-URL: Repository, https://github.com/markrussinovich/dbgview-mcp
Project-URL: Issues, https://github.com/markrussinovich/dbgview-mcp/issues
Author: Mark Russinovich
License-Expression: MIT
Keywords: debug,debugview,mcp,outputdebugstring,windows
Classifier: Development Status :: 4 - Beta
Classifier: Environment :: Win32 (MS Windows)
Classifier: Intended Audience :: Developers
Classifier: License :: OSI Approved :: MIT License
Classifier: Operating System :: Microsoft :: Windows
Classifier: Programming Language :: Python :: 3
Classifier: Programming Language :: Python :: 3.10
Classifier: Programming Language :: Python :: 3.11
Classifier: Programming Language :: Python :: 3.12
Classifier: Programming Language :: Python :: 3.13
Classifier: Topic :: Software Development :: Debuggers
Requires-Python: >=3.10
Requires-Dist: mcp>=1.0.0
Requires-Dist: psutil>=5.9.0
Provides-Extra: dev
Requires-Dist: pytest-asyncio>=0.21.0; extra == 'dev'
Requires-Dist: pytest>=7.0.0; extra == 'dev'
